tivar/__init__.py
tivar/lib/__init__.py
tivar/lib/cv2best_r05.model
tivar/lib/cv2best_r1.model
tivar/lib/cv2best_r2.model
tivar/lib/cv2best_r3.model
tivar/lib/cv2best_r4.model
tivar/lib/cv2best_r5.model
tivar/lib/my_nn_6_r05.model
tivar/lib/my_nn_6_r1.model
tivar/lib/my_nn_6_r2.model
tivar/lib/my_nn_6_r3.model
tivar/lib/my_nn_6_r4.model
tivar/lib/my_nn_6_r5.model
tivar/run/__init__.py
tivar/run/diff.py
tivar/run/predict.py
tivar/zbio/__init__.py
tivar/zbio/bed.py
tivar/zbio/fa.py
tivar/zbio/gtf.py
tivar/zbio/interval.py
tivar/zbio/io.py
tivar/zbio/mut.py
tivar/zbio/tools.py
tivar-0.1.3.data/scripts/tivar
tivar-0.1.3.dist-info/METADATA
tivar-0.1.3.dist-info/WHEEL
tivar-0.1.3.dist-info/entry_points.txt
tivar-0.1.3.dist-info/top_level.txt
tivar-0.1.3.dist-info/RECORD
