Metadata-Version: 2.1
Name: tivar
Version: 0.1.3
Summary: Translation Initiation Variation
Home-page: https://github.com/zhpn1024/TIVar
Author: Peng Zhang
Author-email: zhpn1024@163.com
Project-URL: Bug Reports, https://github.com/zhpn1024/TIVar/issues
Project-URL: Source, https://github.com/zhpn1024/TIVar
Keywords: translation,initiation,RNA,variation
Classifier: Development Status :: 3 - Alpha
Classifier: Intended Audience :: Developers
Classifier: Topic :: Software Development :: Build Tools
Classifier: License :: OSI Approved :: MIT License
Classifier: Programming Language :: Python :: 3
Classifier: Programming Language :: Python :: 3.7
Classifier: Programming Language :: Python :: 3.8
Classifier: Programming Language :: Python :: 3.9
Classifier: Programming Language :: Python :: 3.10
Classifier: Programming Language :: Python :: 3 :: Only
Requires-Python: >=3.4, <4
Requires-Dist: torch >=1.13.1
Requires-Dist: numpy >=1.21.6
Provides-Extra: dev
Requires-Dist: check-manifest ; extra == 'dev'
Provides-Extra: test
Requires-Dist: coverage ; extra == 'test'
